setup.py
django_temporal/__init__.py
django_temporal/utils.py
django_temporal.egg-info/PKG-INFO
django_temporal.egg-info/SOURCES.txt
django_temporal.egg-info/dependency_links.txt
django_temporal.egg-info/top_level.txt
django_temporal/db/__init__.py
django_temporal/db/backends/__init__.py
django_temporal/db/backends/util.py
django_temporal/db/backends/postgresql/__init__.py
django_temporal/db/backends/postgresql/base.py
django_temporal/db/backends/postgresql/creation.py
django_temporal/db/backends/postgresql/operations.py
django_temporal/db/models/__init__.py
django_temporal/db/models/fields.py
django_temporal/db/models/manager.py
django_temporal/db/models/query.py
django_temporal/db/models/sql/__init__.py
django_temporal/db/models/sql/query.py
django_temporal/db/models/sql/where.py