Metadata-Version: 1.1
Name: django-temporal
Version: 0.3
Summary: Temporal database extension for Django
Home-page: http://github.com/zejn/django_temporal
Author: Gasper Zejn
Author-email: zejn@kiberpipa.org
License: UNKNOWN
Platform: UNKNOWN
Classifier: Development Status :: 4 - Beta
Classifier: Intended Audience :: Developers
Classifier: Topic :: Database
Classifier: Framework :: Django
Classifier: License :: OSI Approved :: BSD License
